pyfunction_package_zhanghpy/__init__.py
pyfunction_package_zhanghpy/common_package.py
pyfunction_package_zhanghpy-0.0.2.dist-info/METADATA
pyfunction_package_zhanghpy-0.0.2.dist-info/WHEEL
pyfunction_package_zhanghpy-0.0.2.dist-info/licenses/LICENSE
pyfunction_package_zhanghpy-0.0.2.dist-info/RECORD
